[
    {
        "activityId": "start-event",
        "activityType": "bpmn:StartEvent:start",
        "processLinkType": "form",
        "formDefinitionName": "start-form-example"
    },
    {
        "activityId": "valtimo-s2t-action",
        "activityType": "bpmn:ServiceTask:start",
        "processLinkType": "plugin",
        "pluginActionDefinitionKey": "speech-to-transcription",
        "pluginConfigurationId": "4ac9a49f-4aeb-4f91-86d9-853fd95a1b33",
        "actionProperties": {
            "filePV": "resourceId",
            "resultPV": "result"
        }
    }
]
